<annotation>
	<folder>pictures_hive1</folder>
	<filename>beehive-2020-08-19_11-19-42.jpg</filename>
	<path>C:\Users\ernil\Documents\hllbar\Bildur\raw_data-002\Raw data\Pictures LE\pictures_hive1\beehive-2020-08-19_11-19-42.jpg</path>
	<source>
		<database>Unknown</database>
	</source>
	<size>
		<width>3280</width>
		<height>2464</height>
		<depth>3</depth>
	</size>
	<segmented>0</segmented>
	<object>
		<name>Worker/female</name>
		<pose>Unspecified</pose>
		<truncated>0</truncated>
		<difficult>0</difficult>
		<bndbox>
			<xmin>318</xmin>
			<ymin>127</ymin>
			<xmax>808</xmax>
			<ymax>535</ymax>
		</bndbox>
	</object>
	<object>
		<name>Worker/female</name>
		<pose>Unspecified</pose>
		<truncated>0</truncated>
		<difficult>0</difficult>
		<bndbox>
			<xmin>1833</xmin>
			<ymin>533</ymin>
			<xmax>2180</xmax>
			<ymax>902</ymax>
		</bndbox>
	</object>
	<object>
		<name>Worker/female</name>
		<pose>Unspecified</pose>
		<truncated>0</truncated>
		<difficult>0</difficult>
		<bndbox>
			<xmin>469</xmin>
			<ymin>1558</ymin>
			<xmax>823</xmax>
			<ymax>1840</ymax>
		</bndbox>
	</object>
	<object>
		<name>Worker/female</name>
		<pose>Unspecified</pose>
		<truncated>0</truncated>
		<difficult>0</difficult>
		<bndbox>
			<xmin>662</xmin>
			<ymin>1943</ymin>
			<xmax>982</xmax>
			<ymax>2379</ymax>
		</bndbox>
	</object>
	<object>
		<name>Unknown/bee</name>
		<pose>Unspecified</pose>
		<truncated>0</truncated>
		<difficult>0</difficult>
		<bndbox>
			<xmin>85</xmin>
			<ymin>1657</ymin>
			<xmax>257</xmax>
			<ymax>1888</ymax>
		</bndbox>
	</object>
	<object>
		<name>Unknown/bee</name>
		<pose>Unspecified</pose>
		<truncated>1</truncated>
		<difficult>0</difficult>
		<bndbox>
			<xmin>1</xmin>
			<ymin>1688</ymin>
			<xmax>72</xmax>
			<ymax>1793</ymax>
		</bndbox>
	</object>
	<object>
		<name>Unknown/bee</name>
		<pose>Unspecified</pose>
		<truncated>0</truncated>
		<difficult>0</difficult>
		<bndbox>
			<xmin>1030</xmin>
			<ymin>1640</ymin>
			<xmax>1239</xmax>
			<ymax>1790</ymax>
		</bndbox>
	</object>
	<object>
		<name>Worker/female</name>
		<pose>Unspecified</pose>
		<truncated>0</truncated>
		<difficult>0</difficult>
		<bndbox>
			<xmin>729</xmin>
			<ymin>1786</ymin>
			<xmax>844</xmax>
			<ymax>1898</ymax>
		</bndbox>
	</object>
	<object>
		<name>Worker/female</name>
		<pose>Unspecified</pose>
		<truncated>1</truncated>
		<difficult>0</difficult>
		<bndbox>
			<xmin>1114</xmin>
			<ymin>2114</ymin>
			<xmax>1435</xmax>
			<ymax>2464</ymax>
		</bndbox>
	</object>
	<object>
		<name>Worker/female</name>
		<pose>Unspecified</pose>
		<truncated>0</truncated>
		<difficult>0</difficult>
		<bndbox>
			<xmin>1718</xmin>
			<ymin>1681</ymin>
			<xmax>2037</xmax>
			<ymax>2052</ymax>
		</bndbox>
	</object>
	<object>
		<name>Worker/female</name>
		<pose>Unspecified</pose>
		<truncated>0</truncated>
		<difficult>0</difficult>
		<bndbox>
			<xmin>2595</xmin>
			<ymin>1777</ymin>
			<xmax>2949</xmax>
			<ymax>2195</ymax>
		</bndbox>
	</object>
	<object>
		<name>Worker/female</name>
		<pose>Unspecified</pose>
		<truncated>0</truncated>
		<difficult>0</difficult>
		<bndbox>
			<xmin>2811</xmin>
			<ymin>2029</ymin>
			<xmax>3224</xmax>
			<ymax>2431</ymax>
		</bndbox>
	</object>
</annotation>
