<annotation>
	<folder>pictures_hive1</folder>
	<filename>beehive-2020-08-15_09-08-03.jpg</filename>
	<path>C:\Users\ernil\Documents\hllbar\Bildur\raw_data-002\Raw data\Pictures LE\pictures_hive1\beehive-2020-08-15_09-08-03.jpg</path>
	<source>
		<database>Unknown</database>
	</source>
	<size>
		<width>3280</width>
		<height>2464</height>
		<depth>3</depth>
	</size>
	<segmented>0</segmented>
	<object>
		<name>Unknown/bee</name>
		<pose>Unspecified</pose>
		<truncated>0</truncated>
		<difficult>0</difficult>
		<bndbox>
			<xmin>131</xmin>
			<ymin>1829</ymin>
			<xmax>256</xmax>
			<ymax>2186</ymax>
		</bndbox>
	</object>
	<object>
		<name>Worker/female</name>
		<pose>Unspecified</pose>
		<truncated>0</truncated>
		<difficult>0</difficult>
		<bndbox>
			<xmin>239</xmin>
			<ymin>1751</ymin>
			<xmax>382</xmax>
			<ymax>2153</ymax>
		</bndbox>
	</object>
	<object>
		<name>Unknown/bee</name>
		<pose>Unspecified</pose>
		<truncated>0</truncated>
		<difficult>0</difficult>
		<bndbox>
			<xmin>327</xmin>
			<ymin>1732</ymin>
			<xmax>642</xmax>
			<ymax>1998</ymax>
		</bndbox>
	</object>
	<object>
		<name>Worker/female</name>
		<pose>Unspecified</pose>
		<truncated>0</truncated>
		<difficult>0</difficult>
		<bndbox>
			<xmin>354</xmin>
			<ymin>1962</ymin>
			<xmax>666</xmax>
			<ymax>2332</ymax>
		</bndbox>
	</object>
	<object>
		<name>Worker/female</name>
		<pose>Unspecified</pose>
		<truncated>0</truncated>
		<difficult>0</difficult>
		<bndbox>
			<xmin>489</xmin>
			<ymin>1617</ymin>
			<xmax>831</xmax>
			<ymax>2012</ymax>
		</bndbox>
	</object>
	<object>
		<name>Worker/female</name>
		<pose>Unspecified</pose>
		<truncated>0</truncated>
		<difficult>0</difficult>
		<bndbox>
			<xmin>783</xmin>
			<ymin>1807</ymin>
			<xmax>1116</xmax>
			<ymax>2032</ymax>
		</bndbox>
	</object>
	<object>
		<name>Worker/female</name>
		<pose>Unspecified</pose>
		<truncated>0</truncated>
		<difficult>0</difficult>
		<bndbox>
			<xmin>938</xmin>
			<ymin>1612</ymin>
			<xmax>1271</xmax>
			<ymax>1838</ymax>
		</bndbox>
	</object>
	<object>
		<name>Worker/female</name>
		<pose>Unspecified</pose>
		<truncated>0</truncated>
		<difficult>0</difficult>
		<bndbox>
			<xmin>1067</xmin>
			<ymin>1717</ymin>
			<xmax>1375</xmax>
			<ymax>2033</ymax>
		</bndbox>
	</object>
	<object>
		<name>Worker/female</name>
		<pose>Unspecified</pose>
		<truncated>0</truncated>
		<difficult>0</difficult>
		<bndbox>
			<xmin>2133</xmin>
			<ymin>1123</ymin>
			<xmax>2456</xmax>
			<ymax>1457</ymax>
		</bndbox>
	</object>
	<object>
		<name>Worker/female</name>
		<pose>Unspecified</pose>
		<truncated>0</truncated>
		<difficult>0</difficult>
		<bndbox>
			<xmin>2204</xmin>
			<ymin>1537</ymin>
			<xmax>2426</xmax>
			<ymax>1864</ymax>
		</bndbox>
	</object>
</annotation>
