<annotation>
	<folder>pictures_hive1</folder>
	<filename>beehive-2020-08-19_11-22-52.jpg</filename>
	<path>C:\Users\ernil\Documents\hllbar\Bildur\raw_data-002\Raw data\Pictures LE\pictures_hive1\beehive-2020-08-19_11-22-52.jpg</path>
	<source>
		<database>Unknown</database>
	</source>
	<size>
		<width>3280</width>
		<height>2464</height>
		<depth>3</depth>
	</size>
	<segmented>0</segmented>
	<object>
		<name>Worker/female</name>
		<pose>Unspecified</pose>
		<truncated>0</truncated>
		<difficult>0</difficult>
		<bndbox>
			<xmin>205</xmin>
			<ymin>184</ymin>
			<xmax>621</xmax>
			<ymax>525</ymax>
		</bndbox>
	</object>
	<object>
		<name>Worker/female</name>
		<pose>Unspecified</pose>
		<truncated>1</truncated>
		<difficult>0</difficult>
		<bndbox>
			<xmin>1</xmin>
			<ymin>207</ymin>
			<xmax>218</xmax>
			<ymax>771</ymax>
		</bndbox>
	</object>
	<object>
		<name>Unknown/bee</name>
		<pose>Unspecified</pose>
		<truncated>1</truncated>
		<difficult>0</difficult>
		<bndbox>
			<xmin>367</xmin>
			<ymin>1</ymin>
			<xmax>613</xmax>
			<ymax>217</ymax>
		</bndbox>
	</object>
	<object>
		<name>Worker/female</name>
		<pose>Unspecified</pose>
		<truncated>0</truncated>
		<difficult>0</difficult>
		<bndbox>
			<xmin>595</xmin>
			<ymin>1035</ymin>
			<xmax>897</xmax>
			<ymax>1468</ymax>
		</bndbox>
	</object>
	<object>
		<name>Worker/female</name>
		<pose>Unspecified</pose>
		<truncated>0</truncated>
		<difficult>0</difficult>
		<bndbox>
			<xmin>2777</xmin>
			<ymin>2045</ymin>
			<xmax>3153</xmax>
			<ymax>2412</ymax>
		</bndbox>
	</object>
	<object>
		<name>Worker/female</name>
		<pose>Unspecified</pose>
		<truncated>0</truncated>
		<difficult>0</difficult>
		<bndbox>
			<xmin>2392</xmin>
			<ymin>1680</ymin>
			<xmax>2771</xmax>
			<ymax>2048</ymax>
		</bndbox>
	</object>
	<object>
		<name>Unknown/bee</name>
		<pose>Unspecified</pose>
		<truncated>0</truncated>
		<difficult>0</difficult>
		<bndbox>
			<xmin>1919</xmin>
			<ymin>1621</ymin>
			<xmax>2084</xmax>
			<ymax>1756</ymax>
		</bndbox>
	</object>
	<object>
		<name>Worker/female</name>
		<pose>Unspecified</pose>
		<truncated>1</truncated>
		<difficult>0</difficult>
		<bndbox>
			<xmin>2717</xmin>
			<ymin>2333</ymin>
			<xmax>3057</xmax>
			<ymax>2464</ymax>
		</bndbox>
	</object>
	<object>
		<name>Worker/female</name>
		<pose>Unspecified</pose>
		<truncated>0</truncated>
		<difficult>0</difficult>
		<bndbox>
			<xmin>2332</xmin>
			<ymin>1933</ymin>
			<xmax>2589</xmax>
			<ymax>2336</ymax>
		</bndbox>
	</object>
	<object>
		<name>Worker/female</name>
		<pose>Unspecified</pose>
		<truncated>1</truncated>
		<difficult>0</difficult>
		<bndbox>
			<xmin>2428</xmin>
			<ymin>2247</ymin>
			<xmax>2718</xmax>
			<ymax>2464</ymax>
		</bndbox>
	</object>
	<object>
		<name>Unknown/bee</name>
		<pose>Unspecified</pose>
		<truncated>0</truncated>
		<difficult>0</difficult>
		<bndbox>
			<xmin>2153</xmin>
			<ymin>1989</ymin>
			<xmax>2373</xmax>
			<ymax>2353</ymax>
		</bndbox>
	</object>
	<object>
		<name>Unknown/bee</name>
		<pose>Unspecified</pose>
		<truncated>0</truncated>
		<difficult>0</difficult>
		<bndbox>
			<xmin>1996</xmin>
			<ymin>1783</ymin>
			<xmax>2259</xmax>
			<ymax>2195</ymax>
		</bndbox>
	</object>
	<object>
		<name>Unknown/bee</name>
		<pose>Unspecified</pose>
		<truncated>0</truncated>
		<difficult>0</difficult>
		<bndbox>
			<xmin>1884</xmin>
			<ymin>1827</ymin>
			<xmax>2057</xmax>
			<ymax>2189</ymax>
		</bndbox>
	</object>
	<object>
		<name>Worker/female</name>
		<pose>Unspecified</pose>
		<truncated>0</truncated>
		<difficult>0</difficult>
		<bndbox>
			<xmin>1687</xmin>
			<ymin>1656</ymin>
			<xmax>1896</xmax>
			<ymax>2018</ymax>
		</bndbox>
	</object>
	<object>
		<name>Worker/female</name>
		<pose>Unspecified</pose>
		<truncated>0</truncated>
		<difficult>0</difficult>
		<bndbox>
			<xmin>1746</xmin>
			<ymin>2015</ymin>
			<xmax>1970</xmax>
			<ymax>2450</ymax>
		</bndbox>
	</object>
	<object>
		<name>Unknown/bee</name>
		<pose>Unspecified</pose>
		<truncated>0</truncated>
		<difficult>0</difficult>
		<bndbox>
			<xmin>1699</xmin>
			<ymin>1695</ymin>
			<xmax>1777</xmax>
			<ymax>2026</ymax>
		</bndbox>
	</object>
	<object>
		<name>Worker/female</name>
		<pose>Unspecified</pose>
		<truncated>0</truncated>
		<difficult>0</difficult>
		<bndbox>
			<xmin>1349</xmin>
			<ymin>1652</ymin>
			<xmax>1647</xmax>
			<ymax>1960</ymax>
		</bndbox>
	</object>
	<object>
		<name>Worker/female</name>
		<pose>Unspecified</pose>
		<truncated>0</truncated>
		<difficult>0</difficult>
		<bndbox>
			<xmin>1322</xmin>
			<ymin>1895</ymin>
			<xmax>1615</xmax>
			<ymax>2298</ymax>
		</bndbox>
	</object>
	<object>
		<name>Worker/female</name>
		<pose>Unspecified</pose>
		<truncated>0</truncated>
		<difficult>0</difficult>
		<bndbox>
			<xmin>762</xmin>
			<ymin>1803</ymin>
			<xmax>1157</xmax>
			<ymax>2167</ymax>
		</bndbox>
	</object>
	<object>
		<name>Unknown/bee</name>
		<pose>Unspecified</pose>
		<truncated>0</truncated>
		<difficult>0</difficult>
		<bndbox>
			<xmin>563</xmin>
			<ymin>1974</ymin>
			<xmax>866</xmax>
			<ymax>2240</ymax>
		</bndbox>
	</object>
	<object>
		<name>Unknown/bee</name>
		<pose>Unspecified</pose>
		<truncated>0</truncated>
		<difficult>0</difficult>
		<bndbox>
			<xmin>173</xmin>
			<ymin>1805</ymin>
			<xmax>510</xmax>
			<ymax>2203</ymax>
		</bndbox>
	</object>
	<object>
		<name>Unknown/bee</name>
		<pose>Unspecified</pose>
		<truncated>0</truncated>
		<difficult>0</difficult>
		<bndbox>
			<xmin>552</xmin>
			<ymin>1662</ymin>
			<xmax>824</xmax>
			<ymax>1832</ymax>
		</bndbox>
	</object>
	<object>
		<name>Worker/female</name>
		<pose>Unspecified</pose>
		<truncated>1</truncated>
		<difficult>0</difficult>
		<bndbox>
			<xmin>751</xmin>
			<ymin>2072</ymin>
			<xmax>1119</xmax>
			<ymax>2464</ymax>
		</bndbox>
	</object>
	<object>
		<name>Worker/female</name>
		<pose>Unspecified</pose>
		<truncated>1</truncated>
		<difficult>0</difficult>
		<bndbox>
			<xmin>576</xmin>
			<ymin>2160</ymin>
			<xmax>856</xmax>
			<ymax>2464</ymax>
		</bndbox>
	</object>
	<object>
		<name>Worker/female</name>
		<pose>Unspecified</pose>
		<truncated>0</truncated>
		<difficult>0</difficult>
		<bndbox>
			<xmin>962</xmin>
			<ymin>1320</ymin>
			<xmax>1397</xmax>
			<ymax>1694</ymax>
		</bndbox>
	</object>
	<object>
		<name>Unknown/bee</name>
		<pose>Unspecified</pose>
		<truncated>1</truncated>
		<difficult>0</difficult>
		<bndbox>
			<xmin>1</xmin>
			<ymin>1866</ymin>
			<xmax>228</xmax>
			<ymax>2172</ymax>
		</bndbox>
	</object>
	<object>
		<name>Unknown/bee</name>
		<pose>Unspecified</pose>
		<truncated>1</truncated>
		<difficult>0</difficult>
		<bndbox>
			<xmin>1</xmin>
			<ymin>2056</ymin>
			<xmax>218</xmax>
			<ymax>2425</ymax>
		</bndbox>
	</object>
</annotation>
