<annotation>
	<folder>pictures_hive1</folder>
	<filename>beehive-2020-08-15_09-37-08.jpg</filename>
	<path>C:\Users\ernil\Documents\hllbar\Bildur\raw_data-002\Raw data\Pictures LE\pictures_hive1\beehive-2020-08-15_09-37-08.jpg</path>
	<source>
		<database>Unknown</database>
	</source>
	<size>
		<width>3280</width>
		<height>2464</height>
		<depth>3</depth>
	</size>
	<segmented>0</segmented>
	<object>
		<name>Worker/female</name>
		<pose>Unspecified</pose>
		<truncated>0</truncated>
		<difficult>0</difficult>
		<bndbox>
			<xmin>2490</xmin>
			<ymin>1238</ymin>
			<xmax>2900</xmax>
			<ymax>1625</ymax>
		</bndbox>
	</object>
	<object>
		<name>Unknown/bee</name>
		<pose>Unspecified</pose>
		<truncated>0</truncated>
		<difficult>0</difficult>
		<bndbox>
			<xmin>43</xmin>
			<ymin>1705</ymin>
			<xmax>317</xmax>
			<ymax>1910</ymax>
		</bndbox>
	</object>
	<object>
		<name>Unknown/bee</name>
		<pose>Unspecified</pose>
		<truncated>0</truncated>
		<difficult>0</difficult>
		<bndbox>
			<xmin>24</xmin>
			<ymin>1908</ymin>
			<xmax>454</xmax>
			<ymax>2255</ymax>
		</bndbox>
	</object>
	<object>
		<name>Worker/female</name>
		<pose>Unspecified</pose>
		<truncated>1</truncated>
		<difficult>0</difficult>
		<bndbox>
			<xmin>1</xmin>
			<ymin>1915</ymin>
			<xmax>110</xmax>
			<ymax>2255</ymax>
		</bndbox>
	</object>
</annotation>
