<annotation>
	<folder>images</folder>
	<filename>hive001.jpg</filename>
	<path>C:\Users\Gustaf\Documents\GitHub\ENM156-Projekt\data\pollen_detection_data\images\hive001.jpg</path>
	<source>
		<database>Unknown</database>
	</source>
	<size>
		<width>590</width>
		<height>460</height>
		<depth>3</depth>
	</size>
	<segmented>0</segmented>
	<object>
		<name>Worker/female</name>
		<pose>Unspecified</pose>
		<truncated>0</truncated>
		<difficult>0</difficult>
		<bndbox>
			<xmin>34</xmin>
			<ymin>169</ymin>
			<xmax>113</xmax>
			<ymax>241</ymax>
		</bndbox>
	</object>
	<object>
		<name>Worker/female</name>
		<pose>Unspecified</pose>
		<truncated>0</truncated>
		<difficult>0</difficult>
		<bndbox>
			<xmin>349</xmin>
			<ymin>177</ymin>
			<xmax>410</xmax>
			<ymax>239</ymax>
		</bndbox>
	</object>
	<object>
		<name>Worker/female</name>
		<pose>Unspecified</pose>
		<truncated>0</truncated>
		<difficult>0</difficult>
		<bndbox>
			<xmin>338</xmin>
			<ymin>140</ymin>
			<xmax>393</xmax>
			<ymax>185</ymax>
		</bndbox>
	</object>
	<object>
		<name>Worker/female</name>
		<pose>Unspecified</pose>
		<truncated>0</truncated>
		<difficult>0</difficult>
		<bndbox>
			<xmin>509</xmin>
			<ymin>147</ymin>
			<xmax>586</xmax>
			<ymax>217</ymax>
		</bndbox>
	</object>
	<object>
		<name>Worker/female</name>
		<pose>Unspecified</pose>
		<truncated>0</truncated>
		<difficult>0</difficult>
		<bndbox>
			<xmin>407</xmin>
			<ymin>137</ymin>
			<xmax>443</xmax>
			<ymax>176</ymax>
		</bndbox>
	</object>
	<object>
		<name>Unknown/bee</name>
		<pose>Unspecified</pose>
		<truncated>0</truncated>
		<difficult>0</difficult>
		<bndbox>
			<xmin>461</xmin>
			<ymin>138</ymin>
			<xmax>487</xmax>
			<ymax>153</ymax>
		</bndbox>
	</object>
	<object>
		<name>Unknown/bee</name>
		<pose>Unspecified</pose>
		<truncated>0</truncated>
		<difficult>0</difficult>
		<bndbox>
			<xmin>495</xmin>
			<ymin>137</ymin>
			<xmax>556</xmax>
			<ymax>161</ymax>
		</bndbox>
	</object>
	<object>
		<name>Worker/female</name>
		<pose>Unspecified</pose>
		<truncated>0</truncated>
		<difficult>0</difficult>
		<bndbox>
			<xmin>471</xmin>
			<ymin>9</ymin>
			<xmax>577</xmax>
			<ymax>79</ymax>
		</bndbox>
	</object>
</annotation>
